wxflow/__init__.py
wxflow/attrdict.py
wxflow/configuration.py
wxflow/exceptions.py
wxflow/executable.py
wxflow/factory.py
wxflow/file_utils.py
wxflow/fsutils.py
wxflow/hsi.py
wxflow/htar.py
wxflow/jinja.py
wxflow/logger.py
wxflow/schema.py
wxflow/sqlitedb.py
wxflow/task.py
wxflow/template.py
wxflow/timetools.py
wxflow/utils.py
wxflow/yaml_file.py
wxflow-0.3.0.dist-info/licenses/LICENSE.md
wxflow-0.3.0.dist-info/METADATA
wxflow-0.3.0.dist-info/WHEEL
wxflow-0.3.0.dist-info/top_level.txt
wxflow-0.3.0.dist-info/RECORD
